{
  "id": "WQ-1119",
  "issueId": "1128449",
  "key": "WQ-1119",
  "summary": "Startup Screen - After Log Out",
  "description": "GIVEN a logged in user has logged out\r\nAND the app has been closed",
  "status": "Done",
  "testType": "Manual",
  "scenarioType": null,
  "gherkin": null,
  "unstructured": null,
  "steps": [
    {
      "id": "8c2c8060-b853-4e76-924a-84952daa6415",
      "action": "WHEN the user launches the app from a closed state",
      "data": "",
      "result": "THEN the Startup Screen doesn't display\r\nAND the Home page displays"
    }
  ]
}