{
  "id": "WQ-1649",
  "issueId": "1129066",
  "key": "WQ-1649",
  "summary": "registerDevice is called when logging out",
  "description": "GIVEN",
  "status": "Done",
  "testType": "Manual",
  "scenarioType": null,
  "gherkin": null,
  "unstructured": null,
  "steps": [
    {
      "id": "c20a3a66-a97f-450b-9f00-fffa9eb02dd1",
      "action": "WHEN a user logs out of the app\r\nAND are in the MLB experience",
      "data": "",
      "result": "THEN clients should make a registerDevice request to Media-Gateway\r\nAND can be verified by searching \"graphql\" in the Network tab of browser dev tools\r\nAND \"clientExperience\", \"deviceId\", \"entitlements\", and \"sessionId\" are present in the \"registerDevice\" call\r\nAND an \"accessToken\" is not present within \"mlbAuth\" in Redux"
    }
  ]
}