{
  "id": "WQ-3253",
  "issueId": "1220427",
  "key": "WQ-3253",
  "summary": "Hero/Featured Space UI - Game (Pre-Game Hide Spoilers ON)",
  "description": "GIVE a user has launched the MLB.tv app\n\nAND Hide Spoilers is set to ON\n\nAND a game in a Pre-Game state is present in the Hero/Featured Space\n\n\n\nNOTE: Figma designs for Card States: [https://www.figma.com/design/rGAWoDJL0fx7RTxv0er9U5/MLB.TV-Connected-Device-Developer-Spec?node-id=179-99561&t=2GMcHnOGaIH6wtRZ-0|https://www.figma.com/design/rGAWoDJL0fx7RTxv0er9U5/MLB.TV-Connected-Device-Developer-Spec?node-id=179-99561&t=2GMcHnOGaIH6wtRZ-0|smart-link] ",
  "status": "Done",
  "testType": "Manual",
  "scenarioType": null,
  "gherkin": null,
  "unstructured": null,
  "steps": [
    {
      "id": "1bf48886-11f5-42be-b1ef-5702585e92d2",
      "action": "WHEN a user is on the Home page\n\nAND Game content is displayed in the Hero/Featured space",
      "data": "",
      "result": "THEN the featured game image is displayed on the right 2/3 of the screen\n\nAND the featured game image has a white border around the image indicating focus\n\nAND the featured game image does not have a gradient applied\n\nAND the featured game details are displayed to the left of the featured image, below the navigation header buttons (See attached screenshots and Figma designs for reference)"
    }
  ]
}